{
    "country_code": "RW",
    "visa_type": "TOURIST",
    "template_ref": "AFRICA_EVISA",
    "overrides": {
        "meta": {
            "fee_euro_approx": "50 USD (30 Days)",
            "fee_inr_approx": 4200,
            "processing_time_standard": "3-7 Working Days (or On Arrival)",
            "max_stay": "30 Days",
            "passport_validity": "6 months"
        },
        "steps_flow": [
            {
                "step_order": 1,
                "title": "Choose Method",
                "description": "Apply online via Irembo portal OR get Visa on Arrival."
            },
            {
                "step_order": 2,
                "title": "Apply/Travel",
                "description": "If online: Submit and pay. If VOA: Fly to Kigali."
            },
            {
                "step_order": 3,
                "title": "Payment",
                "description": "Pay 50 USD (Online or at Airport)."
            },
            {
                "step_order": 4,
                "title": "Entry",
                "description": "Receive visa stamp."
            }
        ]
    },
    "eligibility": null
}